alignMAP/__init__.py
alignMAP/alignValues.py
alignMAP/genDPOdata.py
alignMAP/gendata.py
alignMAP/gendataGUI.py
alignMAP/generate-alpacaFinetune.py
alignMAP/getDPOsoup.py
alignMAP/mergeProcessor.py
alignMAP/plot_cal_winrate.py
alignMAP/plot_pairwise_pareto.py
alignMAP/plot_radar_tabresults.py
alignMAP/plot_rand_lambda_MAP_region.py
alignMAP/plot_reward_dist.py
alignMAP/plot_sequential_baseline.py
alignMAP/plot_tab_in_quantiles.py
alignMAP/rewardProcessor.py
alignMAP/rewardTrainer.py
alignMAP/submit_DPO_job.py
alignMAP/submit_MAP-DPO-PPO_comparison.py
alignMAP/submit_MC-aligned_pipeline.py
alignMAP/submit_PPO-aligned_pipeline.py
alignMAP/submit_jobs.py
alignMAP/submit_perplexity_correction.py
alignMAP/submit_soup.py
alignMAP/tokenValueDecoder.py
alignMAP/trainDPO.py
alignMAP/trainPPO.py
alignMAP/utils.py
alignMAP-1.0.0.dist-info/LICENSE
alignMAP-1.0.0.dist-info/METADATA
alignMAP-1.0.0.dist-info/WHEEL
alignMAP-1.0.0.dist-info/top_level.txt
alignMAP-1.0.0.dist-info/RECORD
