Metadata-Version: 2.1
Name: alignMAP
Version: 1.0.0
Summary: Multi-Human-Value Alignment Palette (MAP) offers a first-principle approach to align AI systems with diverse, dynamically defined human values.
Home-page: https://github.com/wang8740/MAP
Author: Xinran Wang
Author-email: wang8740@umn.edu
Classifier: Programming Language :: Python :: 3
Classifier: License :: OSI Approved :: MIT License
Classifier: Operating System :: OS Independent
Requires-Python: >=3.8
License-File: LICENSE
Requires-Dist: torch>=2.4.0
Requires-Dist: torchaudio>=2.4.1
Requires-Dist: torchvision>=0.19.1
Requires-Dist: transformers==4.44.2
Requires-Dist: scikit-learn==1.3.2
Requires-Dist: scipy==1.5.4
Requires-Dist: pandas==2.0.3
Requires-Dist: tqdm==4.66.5
Requires-Dist: sentencepiece==0.2.0
Requires-Dist: safetensors==0.4.5
Requires-Dist: fastapi==0.115.0
Requires-Dist: uvicorn==0.30.6
Requires-Dist: wandb==0.18.1
Requires-Dist: gradio==3.43.1
Requires-Dist: sphinx==7.1.2
Requires-Dist: sphinx-rtd-theme==3.0.1
Requires-Dist: sphinxcontrib-mermaid==1.0.0
Requires-Dist: dataset==1.6.2
Requires-Dist: datasets==3.0.0
Requires-Dist: huggingface-hub==0.25.0
